Metadata-Version: 2.1
Name: lazyface
Version: 0.0.1
Summary: lazyface
Home-page: https://github.com/alvations/lazyface
Author: 
License: UNKNOWN
Platform: UNKNOWN
Classifier: Programming Language :: Python :: 3
Classifier: License :: OSI Approved :: MIT License
Classifier: Operating System :: OS Independent
License-File: LICENSE
